blog/__init__.py
blog/admin.py
blog/apps.py
blog/forms.py
blog/managers.py
blog/models.py
blog/settings.py
blog/signals.py
blog/urls.py
blog/views.py
blog/middleware/view_counter.py
blog/migrations/0001_initial.py
blog/migrations/0002_add_view_count.py
blog/migrations/0003_ckeditor_content_field.py
blog/migrations/__init__.py
blog/static/blog/js/ckeditor_config.js
blog/templates/blog/base.html
blog/templates/blog/post_archive.html
blog/templates/blog/post_archive_month.html
blog/templates/blog/post_archive_year.html
blog/templates/blog/post_detail.html
blog/templates/blog/post_list.html
blog/templates/blog/includes/footer.html
blog/templates/blog/includes/header.html
blog/templates/blog/includes/sidebar.html
blog/templates/blog/includes/view_counter.html
blog/templatetags/__init__.py
blog/templatetags/blog_tags.py
blog/tests/__init__.py
blog/tests/test_ckeditor.py
blog/tests/test_forms.py
blog/tests/test_models.py
blog/tests/test_template_tags.py
blog/tests/test_views.py
django_blog_package-1.0.9.dist-info/licenses/LICENSE
django_blog_package-1.0.9.dist-info/METADATA
django_blog_package-1.0.9.dist-info/WHEEL
django_blog_package-1.0.9.dist-info/top_level.txt
django_blog_package-1.0.9.dist-info/RECORD
