Metadata-Version: 2.4
Name: django-blog-package
Version: 1.0.9
Summary: A reusable Django blog package for adding blog functionality to any Django project
Home-page: https://github.com/josephbraide/django-blog-package
Author: Joseph Braide
Author-email: Joseph Braide <braidej@gmail.com>
License: MIT
Project-URL: Homepage, https://github.com/josephbraide/django-blog-package
Project-URL: Documentation, https://github.com/josephbraide/django-blog-package/blob/main/README.md
Project-URL: Source, https://github.com/josephbraide/django-blog-package
Project-URL: Issues, https://github.com/josephbraide/django-blog-package/issues
Keywords: django,blog,cms,content,posts,articles,comments,categories,tags
Classifier: Development Status :: 4 - Beta
Classifier: Environment :: Web Environment
Classifier: Framework :: Django
Classifier: Framework :: Django :: 4.2
Classifier: Framework :: Django :: 5.0
Classifier: Intended Audience :: Developers
Classifier: License :: OSI Approved :: MIT License
Classifier: Operating System :: OS Independent
Classifier: Programming Language :: Python
Classifier: Programming Language :: Python :: 3
Classifier: Programming Language :: Python :: 3.8
Classifier: Programming Language :: Python :: 3.9
Classifier: Programming Language :: Python :: 3.10
Classifier: Programming Language :: Python :: 3.11
Classifier: Programming Language :: Python :: 3.12
Classifier: Topic :: Internet :: WWW/HTTP
Classifier: Topic :: Internet :: WWW/HTTP :: Dynamic Content
Requires-Python: >=3.8
License-File: LICENSE
Requires-Dist: Django>=4.2
Requires-Dist: Pillow>=9.0
Requires-Dist: django-ckeditor<7.0,>=6.0
Provides-Extra: dev
Requires-Dist: twine>=4.0.0; extra == "dev"
Requires-Dist: wheel>=0.37.0; extra == "dev"
Dynamic: author
Dynamic: home-page
Dynamic: license-file
Dynamic: requires-python
